eecs/__init__.py
eecs/__main__.py
eecs-0.1.0.dist-info/METADATA
eecs-0.1.0.dist-info/WHEEL
eecs-0.1.0.dist-info/top_level.txt
eecs-0.1.0.dist-info/RECORD
