Metadata-Version: 2.1
Name: eecs
Version: 0.1.0
Summary: eecs utils
Home-page: https://github.com/eecsmap/eecs
Author: Wenyang Duan
Author-email: wenyang.duan@gmail.com
License: UNKNOWN
Platform: UNKNOWN
Classifier: Programming Language :: Python :: 3
Classifier: License :: OSI Approved :: MIT License
Classifier: Operating System :: OS Independent
Requires-Python: >=3.10
